inlaws
example
