Metadata-Version: 1.0
Name: django-inlaws
Version: 0.1
Summary: UNKNOWN
Home-page: UNKNOWN
Author: Corey Oordt, Jose Soares, Justin Quick
Author-email: webdev@washingtontimes.com
License: UNKNOWN
Platform: UNKNOWN
